<?xml version="1.0" encoding="UTF-8"?>
<objects serializationModel="Studio.02.01.00">
	<object class="AudioFile" id="{77b7839e-d4cd-48a0-a10f-eb46e2e3e2df}">
		<property name="assetPath">
			<value>Custom Created/Player/Ladder/LadderStep7.wav</value>
		</property>
		<property name="frequencyInKHz">
			<value>48</value>
		</property>
		<property name="channelCount">
			<value>1</value>
		</property>
		<property name="length">
			<value>0.56129166666666663</value>
		</property>
		<relationship name="masterAssetFolder">
			<destination>{ccf96a22-e71e-4232-b834-b96734b35963}</destination>
		</relationship>
	</object>
</objects>
