<?xml version="1.0" encoding="UTF-8"?>
<objects serializationModel="Studio.02.01.00">
	<object class="AudioFile" id="{95c91307-0aa3-4dcc-b627-00c69cb7eccf}">
		<property name="assetPath">
			<value>General Sound Library/Ambience_BRT_Morning_C01_Town_LOOP.wav</value>
		</property>
		<property name="isStreaming">
			<value>true</value>
		</property>
		<property name="frequencyInKHz">
			<value>44.0999985</value>
		</property>
		<property name="channelCount">
			<value>2</value>
		</property>
		<property name="length">
			<value>60.00049886621315</value>
		</property>
		<relationship name="masterAssetFolder">
			<destination>{ccf96a22-e71e-4232-b834-b96734b35963}</destination>
		</relationship>
	</object>
</objects>
